BaiduMapAPI/__init__.py
BaiduMapAPI/api.py
BaiduMapAPI/checkAK.py
BaiduMapAPI/common.py
BaiduMapAPI/export.py
BaiduMapAPI/globals.py
BaiduMapAPI/data/BaiduMap_cityCode_1102.txt
BaiduMapAPI-0.1.2.data/data/BaiduMapAPI/data/BaiduMap_cityCode_1102.txt
BaiduMapAPI-0.1.2.dist-info/LICENSE
BaiduMapAPI-0.1.2.dist-info/METADATA
BaiduMapAPI-0.1.2.dist-info/WHEEL
BaiduMapAPI-0.1.2.dist-info/top_level.txt
BaiduMapAPI-0.1.2.dist-info/RECORD
