Metadata-Version: 2.1
Name: BaiduMapAPI
Version: 0.1.2
Summary: The Package of Baidu Map, with unofficial
Home-page: https://github.com/shikanon/BaiduMapAPI
Author: shikanon
Author-email: account@shikanon.com
License: MIT
Platform: UNKNOWN
Requires-Dist: requests
